api_sports_io_nfl/__init__.py
api_sports_io_nfl/api.py
api_sports_io_nfl/exceptions.py
api_sports_io_nfl-0.0.2.dist-info/LICENSE
api_sports_io_nfl-0.0.2.dist-info/METADATA
api_sports_io_nfl-0.0.2.dist-info/WHEEL
api_sports_io_nfl-0.0.2.dist-info/RECORD
